<?xml version="1.0" encoding="UTF-8"?><commands version="11.2">
<command appiumName="SetDevice(Device)" enable="true" name="SetDevice(Device)">
<parameters>
<parameter appium="true" defaultValue="adb:EVA-L09" description="Device name" name="Title" pattern="" type="application"/>
</parameters>
</command>
<command appiumName="Launch(app)" enable="true" name="Launch(activity, instrument, stopIfRunning)">
<parameters>
<parameter appium="true" defaultValue="com.example.isho.experitestdemo/.Login" description="The application main activity or URL" name="Activity" pattern="" type="launch"/>
<parameter appium="false" defaultValue="true" description="If set to true then will launch in instrument mode" name="Instrument" pattern="" type="bool"/>
<parameter appium="false" defaultValue="true" description="If set to true then will stop the running process before launching it" name="Stop if run" pattern="" type="bool"/>
</parameters>
</command>
<command appiumName="SendKeys(Text)" enable="true" name="SendText(Text)">
<parameters>
<parameter appium="true" defaultValue="ido" description="Text to send" name="Text" pattern="" type="string"/>
</parameters>
</command>
<command appiumName="FindElement and SendKeys(Element, Text)" enable="true" name="ElementSendText(Zone, Element, Index, Text)" x="225" y="641">
<parameters>
<parameter appium="false" defaultValue="NATIVE" description="Select Zone" name="Zone" pattern="" type="zone_no_ocr"/>
<parameter appium="true" defaultValue="hint=Match" description="Select Element" name="Element" pattern="" type="element"/>
<parameter appium="false" defaultValue="0" description="Element index" name="Index" pattern="" type="integer"/>
<parameter appium="true" defaultValue="ido" description="Text to Send" name="Text" pattern="" type="string"/>
</parameters>
</command>
<command appiumName="FindElement and Click(Element)" enable="true" name="Click(Zone, Element, Index, ClickCount)">
<parameters>
<parameter appium="false" defaultValue="WEB" description="Select Zone" name="Zone" pattern="" type="zone"/>
<parameter appium="true" defaultValue="text=stats&#10;&#10;  time: 13:52:18 &#10;  Shekel/Dollar: 0.284543592078&#10;" description="Select Element" name="Element" pattern="" type="element"/>
<parameter appium="false" defaultValue="0" description="Element Order" name="Index" pattern="" type="integer"/>
<parameter appium="false" defaultValue="1" description="Number of Clicks" name="Click Count" pattern="" type="integer"/>
</parameters>
</command>
<command appiumName="FindElement and Click(Element)" enable="true" name="Click(Zone, Element, Index, ClickCount)" x="408" y="668">
<parameters>
<parameter appium="false" defaultValue="NATIVE" description="Select Zone" name="Zone" pattern="" type="zone"/>
<parameter appium="true" defaultValue="text=Game" description="Select Element" name="Element" pattern="" type="element"/>
<parameter appium="false" defaultValue="0" description="Element Order" name="Index" pattern="" type="integer"/>
<parameter appium="false" defaultValue="1" description="Number of Clicks" name="Click Count" pattern="" type="integer"/>
</parameters>
</command>
<command appiumName="FindElement and Click(Element)" enable="true" name="Click(Zone, Element, Index, ClickCount)" x="89" y="312">
<parameters>
<parameter appium="false" defaultValue="NATIVE" description="Select Zone" name="Zone" pattern="" type="zone"/>
<parameter appium="true" defaultValue="text=2.034" description="Select Element" name="Element" pattern="" type="element"/>
<parameter appium="false" defaultValue="0" description="Element Order" name="Index" pattern="" type="integer"/>
<parameter appium="false" defaultValue="1" description="Number of Clicks" name="Click Count" pattern="" type="integer"/>
</parameters>
</command>
<command appiumName="FindElement and Click(Element)" enable="true" name="Click(Zone, Element, Index, ClickCount)" x="89" y="312">
<parameters>
<parameter appium="false" defaultValue="NATIVE" description="Select Zone" name="Zone" pattern="" type="zone"/>
<parameter appium="true" defaultValue="text=2.034" description="Select Element" name="Element" pattern="" type="element"/>
<parameter appium="false" defaultValue="0" description="Element Order" name="Index" pattern="" type="integer"/>
<parameter appium="false" defaultValue="1" description="Number of Clicks" name="Click Count" pattern="" type="integer"/>
</parameters>
</command>
<command appiumName="FindElement and Click(Element)" enable="true" name="Click(Zone, Element, Index, ClickCount)" x="921" y="716">
<parameters>
<parameter appium="false" defaultValue="NATIVE" description="Select Zone" name="Zone" pattern="" type="zone"/>
<parameter appium="true" defaultValue="xpath=//*[@id='clicker_button']" description="Select Element" name="Element" pattern="" type="element"/>
<parameter appium="false" defaultValue="0" description="Element Order" name="Index" pattern="" type="integer"/>
<parameter appium="false" defaultValue="1" description="Number of Clicks" name="Click Count" pattern="" type="integer"/>
</parameters>
</command>
<command appiumName="FindElement and Click(Element)" enable="true" name="Click(Zone, Element, Index, ClickCount)" x="554" y="196">
<parameters>
<parameter appium="false" defaultValue="NATIVE" description="Select Zone" name="Zone" pattern="" type="zone"/>
<parameter appium="true" defaultValue="xpath=//*[@id='clicker_button']" description="Select Element" name="Element" pattern="" type="element"/>
<parameter appium="false" defaultValue="0" description="Element Order" name="Index" pattern="" type="integer"/>
<parameter appium="false" defaultValue="1" description="Number of Clicks" name="Click Count" pattern="" type="integer"/>
</parameters>
</command>
<command appiumName="FindElement and Click(Element)" enable="true" name="Click(Zone, Element, Index, ClickCount)" x="537" y="248">
<parameters>
<parameter appium="false" defaultValue="NATIVE" description="Select Zone" name="Zone" pattern="" type="zone"/>
<parameter appium="true" defaultValue="xpath=//*[@id='clicker_button']" description="Select Element" name="Element" pattern="" type="element"/>
<parameter appium="false" defaultValue="0" description="Element Order" name="Index" pattern="" type="integer"/>
<parameter appium="false" defaultValue="1" description="Number of Clicks" name="Click Count" pattern="" type="integer"/>
</parameters>
</command>
<command appiumName="FindElement and Click(Element)" enable="true" name="Click(Zone, Element, Index, ClickCount)" x="68" y="279">
<parameters>
<parameter appium="false" defaultValue="NATIVE" description="Select Zone" name="Zone" pattern="" type="zone"/>
<parameter appium="true" defaultValue="xpath=//*[@id='clicker_button']" description="Select Element" name="Element" pattern="" type="element"/>
<parameter appium="false" defaultValue="0" description="Element Order" name="Index" pattern="" type="integer"/>
<parameter appium="false" defaultValue="1" description="Number of Clicks" name="Click Count" pattern="" type="integer"/>
</parameters>
</command>
<command appiumName="FindElement and Click(Element)" enable="true" name="Click(Zone, Element, Index, ClickCount)" x="270" y="88">
<parameters>
<parameter appium="false" defaultValue="NATIVE" description="Select Zone" name="Zone" pattern="" type="zone"/>
<parameter appium="true" defaultValue="xpath=//*[@id='clicker_button']" description="Select Element" name="Element" pattern="" type="element"/>
<parameter appium="false" defaultValue="0" description="Element Order" name="Index" pattern="" type="integer"/>
<parameter appium="false" defaultValue="1" description="Number of Clicks" name="Click Count" pattern="" type="integer"/>
</parameters>
</command>
<command appiumName="FindElement and Click(Element)" enable="true" name="Click(Zone, Element, Index, ClickCount)" x="408" y="870">
<parameters>
<parameter appium="false" defaultValue="NATIVE" description="Select Zone" name="Zone" pattern="" type="zone"/>
<parameter appium="true" defaultValue="text=Again" description="Select Element" name="Element" pattern="" type="element"/>
<parameter appium="false" defaultValue="0" description="Element Order" name="Index" pattern="" type="integer"/>
<parameter appium="false" defaultValue="1" description="Number of Clicks" name="Click Count" pattern="" type="integer"/>
</parameters>
</command>
<command appiumName="FindElement and Click(Element)" enable="true" name="Click(Zone, Element, Index, ClickCount)" x="386" y="1555">
<parameters>
<parameter appium="false" defaultValue="NATIVE" description="Select Zone" name="Zone" pattern="" type="zone"/>
<parameter appium="true" defaultValue="xpath=//*[@id='clicker_button']" description="Select Element" name="Element" pattern="" type="element"/>
<parameter appium="false" defaultValue="0" description="Element Order" name="Index" pattern="" type="integer"/>
<parameter appium="false" defaultValue="1" description="Number of Clicks" name="Click Count" pattern="" type="integer"/>
</parameters>
</command>
<command appiumName="FindElement and Click(Element)" enable="true" name="Click(Zone, Element, Index, ClickCount)" x="91" y="1250">
<parameters>
<parameter appium="false" defaultValue="NATIVE" description="Select Zone" name="Zone" pattern="" type="zone"/>
<parameter appium="true" defaultValue="xpath=//*[@id='clicker_button']" description="Select Element" name="Element" pattern="" type="element"/>
<parameter appium="false" defaultValue="0" description="Element Order" name="Index" pattern="" type="integer"/>
<parameter appium="false" defaultValue="1" description="Number of Clicks" name="Click Count" pattern="" type="integer"/>
</parameters>
</command>
<command appiumName="FindElement and Click(Element)" enable="true" name="Click(Zone, Element, Index, ClickCount)" x="289" y="1442">
<parameters>
<parameter appium="false" defaultValue="NATIVE" description="Select Zone" name="Zone" pattern="" type="zone"/>
<parameter appium="true" defaultValue="xpath=//*[@id='clicker_button']" description="Select Element" name="Element" pattern="" type="element"/>
<parameter appium="false" defaultValue="0" description="Element Order" name="Index" pattern="" type="integer"/>
<parameter appium="false" defaultValue="1" description="Number of Clicks" name="Click Count" pattern="" type="integer"/>
</parameters>
</command>
<command appiumName="FindElement and Click(Element)" enable="true" name="Click(Zone, Element, Index, ClickCount)" x="408" y="870">
<parameters>
<parameter appium="false" defaultValue="NATIVE" description="Select Zone" name="Zone" pattern="" type="zone"/>
<parameter appium="true" defaultValue="text=Again" description="Select Element" name="Element" pattern="" type="element"/>
<parameter appium="false" defaultValue="0" description="Element Order" name="Index" pattern="" type="integer"/>
<parameter appium="false" defaultValue="1" description="Number of Clicks" name="Click Count" pattern="" type="integer"/>
</parameters>
</command>
<command appiumName="FindElement and Click(Element)" enable="true" name="Click(Zone, Element, Index, ClickCount)" x="490" y="72">
<parameters>
<parameter appium="false" defaultValue="NATIVE" description="Select Zone" name="Zone" pattern="" type="zone"/>
<parameter appium="true" defaultValue="text=0" description="Select Element" name="Element" pattern="" type="element"/>
<parameter appium="false" defaultValue="0" description="Element Order" name="Index" pattern="" type="integer"/>
<parameter appium="false" defaultValue="1" description="Number of Clicks" name="Click Count" pattern="" type="integer"/>
</parameters>
</command>
<command appiumName="FindElement and Click(Element)" enable="true" name="Click(Zone, Element, Index, ClickCount)" x="204" y="870">
<parameters>
<parameter appium="false" defaultValue="NATIVE" description="Select Zone" name="Zone" pattern="" type="zone"/>
<parameter appium="true" defaultValue="text=Exit" description="Select Element" name="Element" pattern="" type="element"/>
<parameter appium="false" defaultValue="0" description="Element Order" name="Index" pattern="" type="integer"/>
<parameter appium="false" defaultValue="1" description="Number of Clicks" name="Click Count" pattern="" type="integer"/>
</parameters>
</command>
<command appiumName="FindElement and Click(Element)" enable="true" name="Click(Zone, Element, Index, ClickCount)" x="408" y="956">
<parameters>
<parameter appium="false" defaultValue="NATIVE" description="Select Zone" name="Zone" pattern="" type="zone"/>
<parameter appium="true" defaultValue="text=Records" description="Select Element" name="Element" pattern="" type="element"/>
<parameter appium="false" defaultValue="0" description="Element Order" name="Index" pattern="" type="integer"/>
<parameter appium="false" defaultValue="1" description="Number of Clicks" name="Click Count" pattern="" type="integer"/>
</parameters>
</command>
<command appiumName="WaitForElementPresence(Element, Timeout)" enable="true" name="WaitForElement(Zone, Element, Index, Timeout)">
<parameters>
<parameter appium="false" defaultValue="NATIVE" description="Select Zone" name="Zone" pattern="" type="zone"/>
<parameter appium="true" defaultValue="xpath=//*[@class='com.android.internal.policy.PhoneWindow$DecorView']" description="Select Element to Wait For" name="Element" pattern="" type="element"/>
<parameter appium="false" defaultValue="0" description="Element Order" name="Index" pattern="" type="integer"/>
<parameter appium="true" defaultValue="30000" description="Waiting Timeout in MiliSec" name="Timeout" pattern="" type="integer"/>
</parameters>
</command>
<command appiumName="FindElement and Click(Element)" enable="true" name="Click(Zone, Element, Index, ClickCount)">
<parameters>
<parameter appium="false" defaultValue="NATIVE" description="Select Zone" name="Zone" pattern="" type="zone"/>
<parameter appium="true" defaultValue="xpath=//*[@class='com.android.internal.policy.PhoneWindow$DecorView']" description="Select Element" name="Element" pattern="" type="element"/>
<parameter appium="false" defaultValue="0" description="Element Order" name="Index" pattern="" type="integer"/>
<parameter appium="false" defaultValue="1" description="Number of Clicks" name="Click Count" pattern="" type="integer"/>
</parameters>
</command>
</commands>
